claude_token_count/__init__.py
claude_token_count/main.py
claude_token_count-0.1.1.dist-info/METADATA
claude_token_count-0.1.1.dist-info/WHEEL
claude_token_count-0.1.1.dist-info/entry_points.txt
claude_token_count-0.1.1.dist-info/top_level.txt
claude_token_count-0.1.1.dist-info/RECORD
