Metadata-Version: 2.4
Name: claude-token-count
Version: 0.1.1
Summary: CLI to return number of Claude tokens in your text
Author: Sergey Karayev
License-Expression: Apache-2.0
Project-URL: Homepage, https://github.com/sergeyk/claude-token-count
Project-URL: Issues, https://github.com/sergeyk/claude-token-count/issues
Project-URL: CI, https://github.com/sergeyk/claude-token-count/actions
Project-URL: Changelog, https://github.com/sergeyk/claude-token-count/releases
Requires-Python: >=3.10
Requires-Dist: anthropic>=0.64.0
Requires-Dist: click>=8.1
